checkmate_sample/ __init__.py
checkmate_sample/generator.py
checkmate_sample/update_toml.py
checkmate_sample-0.1.1.dist-info/LICENSE
checkmate_sample-0.1.1.dist-info/METADATA
checkmate_sample-0.1.1.dist-info/WHEEL
checkmate_sample-0.1.1.dist-info/top_level.txt
checkmate_sample-0.1.1.dist-info/RECORD
