Metadata-Version: 2.1
Name: checkmate_sample
Version: 0.1.1
Summary: A sample project with checkerboard functionality
Author-email: Thomas Martin <tmartin@ucar.edu>
Project-URL: Homepage, https://github.com/ThomasMGeo/checkmate-sample
Requires-Python: >=3.9
License-File: LICENSE
Requires-Dist: numpy >=1.26.0
Requires-Dist: xarray >=2023.8.0
Requires-Dist: pytest >=7.4.0
